midiogre/__init__.py
midiogre/_version.py
midiogre/augmentations/__init__.py
midiogre/augmentations/duration_shift.py
midiogre/augmentations/note_add.py
midiogre/augmentations/note_delete.py
midiogre/augmentations/onset_time_shift.py
midiogre/augmentations/pitch_shift.py
midiogre/augmentations/tempo_shift.py
midiogre/core/__init__.py
midiogre/core/compositions.py
midiogre/core/conversions.py
midiogre/core/transforms_interface.py
midiogre/core/transforms_viz.py
midiogre-0.1.12.post0.dist-info/licenses/LICENSE
midiogre-0.1.12.post0.dist-info/METADATA
midiogre-0.1.12.post0.dist-info/WHEEL
midiogre-0.1.12.post0.dist-info/top_level.txt
midiogre-0.1.12.post0.dist-info/RECORD
