Metadata-Version: 2.4
Name: midiogre
Version: 0.1.12.post0
Summary: The On-the-fly MIDI Data Augmentation Library!
Author-email: Ashwin Pillay <c6idbv07e@mozmail.com>
License-Expression: MIT
Project-URL: Homepage, https://github.com/a-pillay/MIDIOgre
Project-URL: Documentation, https://a-pillay.github.io/MIDIOgre/
Project-URL: Issue Tracker, https://github.com/a-pillay/MIDIOgre/issues
Classifier: Programming Language :: Python :: 3
Classifier: Operating System :: OS Independent
Classifier: Development Status :: 3 - Alpha
Classifier: Intended Audience :: Developers
Classifier: Intended Audience :: Science/Research
Classifier: Topic :: Multimedia
Classifier: Topic :: Multimedia :: Sound/Audio
Classifier: Topic :: Scientific/Engineering
Classifier: Topic :: Scientific/Engineering :: Artificial Intelligence
Requires-Python: >=3.7
License-File: LICENSE
Requires-Dist: numpy>=1.21.6
Requires-Dist: pretty-midi>=0.2.10
Requires-Dist: torch>=1.13.1
Requires-Dist: mido>=1.2.10
Provides-Extra: extras
Requires-Dist: matplotlib>=3.5.3; extra == "extras"
Provides-Extra: dev
Requires-Dist: pytest>=7.0.0; extra == "dev"
Requires-Dist: pytest-cov>=4.0.0; extra == "dev"
Requires-Dist: black>=22.0.0; extra == "dev"
Requires-Dist: isort>=5.0.0; extra == "dev"
Requires-Dist: sphinx>=4.0.0; extra == "dev"
Requires-Dist: sphinx-rtd-theme>=1.0.0; extra == "dev"
Dynamic: license-file
